pudzu/sandbox/__init__.py
pudzu/sandbox/bamboo.py
pudzu/sandbox/markov.py
pudzu/sandbox/nounce.py
pudzu/sandbox/tinytim.py
pudzu/sandbox/tureen.py
pudzu/sandbox/unicode/Blocks.txt
pudzu/sandbox/unicode/DerivedCoreProperties.txt
pudzu/sandbox/unicode/PropList.txt
pudzu/sandbox/unicode/ScriptExtensions.txt
pudzu/sandbox/unicode/Scripts.txt
pudzu/sandbox/unicode/UnicodeData.txt
pudzu/sandbox/unicode/__init__.py
pudzu/sandbox/unicode/emoji-data.txt
pudzu/sandbox/unicode/unicode.py
pudzu/sandbox/wikipage.py
pudzu-0.9.4.dist-info/LICENSE
pudzu-0.9.4.dist-info/METADATA
pudzu-0.9.4.dist-info/WHEEL
pudzu-0.9.4.dist-info/RECORD
