Metadata-Version: 2.1
Name: pudzu
Version: 0.9.4
Summary: Various dataviz-oriented utilities
Home-page: https://github.com/Udzu/pudzu/
License: MIT
Keywords: pudzu,visualization,pillow,unicode
Author: Uri Granta
Author-email: uri.granta+python@gmail.com
Requires-Python: >=3.8,<4.0
Classifier: License :: OSI Approved :: MIT License
Classifier: Operating System :: OS Independent
Classifier: Programming Language :: Python :: 3
Classifier: Programming Language :: Python :: 3.8
Classifier: Programming Language :: Python :: 3.9
Classifier: Programming Language :: Python :: 3.10
Classifier: Programming Language :: Python :: 3.11
Classifier: Programming Language :: Python :: 3.12
Requires-Dist: beautifulsoup4 (>=4.7.1,<5.0.0)
Requires-Dist: graphviz (>=0.13.2,<0.14.0)
Requires-Dist: lxml (>=4.4.2,<5.0.0)
Requires-Dist: pandas (>=1.4,<2.0)
Requires-Dist: pudzu-charts (>=0.9.3,<0.10.0)
Requires-Dist: pudzu-dates (>=0.9.3,<0.10.0)
Requires-Dist: pudzu-patterns (>=0.9.3,<0.10.0)
Requires-Dist: pudzu-pillar (>=0.9.3,<0.10.0)
Requires-Dist: pudzu-utils (>=0.9.3,<0.10.0)
Requires-Dist: pyparsing (>=3.0,<4.0)
Requires-Dist: requests (>=2.22.0,<3.0.0)
